marshmallow_encrypted/__init__.py
marshmallow_encrypted/crypto.py
marshmallow_encrypted/field.py
marshmallow_encrypted-0.1.0.dist-info/WHEEL
marshmallow_encrypted-0.1.0.dist-info/METADATA
marshmallow_encrypted-0.1.0.dist-info/RECORD
